verkhovna_rada_ukr_pl
