Metadata-Version: 1.0
Name: verkhovna-rada-ukr-pl
Version: 0.2.dev0
Summary: Ukrainian and Poland kind of parlament
Home-page: UNKNOWN
Author: Oleg M
Author-email: oleg.matviiv@gmail.com
License: GPL Free License
Platform: UNKNOWN
